Workbook

Sheet README
B2: Credit Risk Analysis of Tata Motors Ltd.
B4: Project period: April 2026
B6: OBJECTIVE
B7: Evaluate the credit profile of the Tata Motors group (consolidated, FY2021-FY2025) - repayment capacity,
B8: leverage, liquidity and profitability trends - and arrive at an indicative internal credit view.
B10: SCOPE / ENTITY NOTE
B11: This analysis covers the historical consolidated Tata Motors Group (JLR + India commercial and passenger
B12: vehicles) for FY2021-FY2025, the entity previously listed as 'Tata Motors Ltd'. On 1 October 2025 the group
B13: demerged: the commercial-vehicle business was carved out into a newly listed 'Tata Motors Ltd' (formerly
B14: TML Commercial Vehicles Ltd), while the passenger-vehicle and JLR businesses continue under the entity now
B15: listed as 'Tata Motors Passenger Vehicles Ltd'. The FY2021-FY2025 financials analyzed here predate that
B16: split and reflect the group as it was structured and rated throughout the period under review.
... B31: not a rating agency methodology output, and should not be read as an actual credit rating.

Sheet Financial Data
A1: Tata Motors Group - Consolidated Financials, FY2021-FY2025 (Rs. Crore)
A2: Source: Screener.in, compiled from company annual reports / BSE filings
A4: Rs. Crore | B4: FY2021 | C4: FY2022 | D4: FY2023 | E4: FY2024 | F4: FY2025
A5: Net Sales | B5: 249795 | C5: 278454 | D5: 345967 | E5: 434016 | F5: 439695
A6: EBITDA (Operating Profit) | B6: 32287 | C6: 24720 | D6: 31816 | E6: 57809 | F6: 56138
A7: EBITDA Margin % | B7: =B6/B5 -> 0.12925399 | C7: =C6/C5 -> 0.088775884 | D7: =D6/D5 -> 0.091962528 | E7: =E6/E5 -> 0.13319555 | F7: =F6/F5 -> 0.12767487
A8: Depreciation & Amortization | B8: 23547 | C8: 24836 | D8: 24860 | E8: 27239 | F8: 23256
A9: EBIT | B9: =B6-B8 -> 8740 | C9: =C6-C8 -> -116 | D9: =D6-D8 -> 6956 | E9: =E6-E8 -> 30570 | F9: =F6-F8 -> 32882
A10: Interest Expense | B10: 8097 | C10: 9312 | D10: 10225 | E10: 7594 | F10: 5083
A11: Other Income | B11: -11118 | C11: 2424 | D11: 6664 | E11: 4807 | F11: 10852
A12: Profit Before Tax | B12: =B9-B10+B11 -> -10475 | C12: =C9-C10+C11 -> -7004 | D12: =D9-D10+D11 -> 3395 | E12: =E9-E10+E11 -> 27783 | F12: =F9-F10+F11 -> 38651
A13: Net Profit (PAT) | B13: -13395 | C13: -11309 | D13: 2690 | E13: 31807 | F13: 28149
A15: Balance Sheet
A16: Rs. Crore | B16: FY2021 | C16: FY2022 | D16: FY2023 | E16: FY2024 | F16: FY2025
A17: Equity Share Capital | B17: 766 | C17: 766 | D17: 766 | E17: 767 | F17: 736
A18: Reserves & Surplus | B18: 54481 | C18: 43795 | D18: 44556 | E18: 84151 | F18: 115408
A19: Total Net Worth | B19: =B17+B18 -> 55247 | C19: =C17+C18 -> 44561 | D19: =D17+D18 -> 45322 | E19: =E17+E18 -> 84918 | F19: =F17+F18 -> 116144
A20: Total Borrowings | B20: 142131 | C20: 146449 | D20: 134113 | E20: 107264 | F20: 71540
A21: Other Liabilities | B21: 144193 | C21: 138051 | D21: 155239 | E21: 177339 | F21: 189289
A22: Total Liabilities & Equity | B22: =B19+B20+B21 -> 341571 | C22: =C19+C20+C21 -> 329061 | D22: =D19+D20+D21 -> 334674 | E22: =E19+E20+E21 -> 369521 | F22: =F19+F20+F21 -> 376973
A24: Cash Flow
A25: Rs. Crore | B25: FY2021 | C25: FY2022 | D25: FY2023 | E25: FY2024 | F25: FY2025
A26: Cash from Operating Activity (CFO) | B26: 29001 | C26: 14283 | D26: 35388 | E26: 67915 | F26: 63102
A27: Free Cash Flow (reported) | B27: 9146 | C27: -655 | D27: 16443 | E27: 36732 | F27: 26034
A29: Working Capital Days (reported, liquidity proxy) | B29: -112 | C29: -88 | D29: -63 | E29: -55 | F29: -62
A30: ROCE % (reported) | B30: 0.06 | C30: 0.01 | D30: 0.06 | E30: 0.19 | F30: 0.2

Sheet Ratio Analysis
A1: Credit Ratio Analysis, FY2021-FY2025
A3: Ratio | B3: FY2021 | C3: FY2022 | D3: FY2023 | E3: FY2024 | F3: FY2025
A4: Leverage
A5: Debt-to-Equity | B5: ='Financial Data'!B20/'Financial Data'!B19 -> 2.5726465 | C5: ='Financial Data'!C20/'Financial Data'!C19 -> 3.2864837 | D5: ='Financial Data'!D20/'Financial Data'!D19 -> 2.9591148 | E5: ='Financial Data'!E20/'Financial Data'!E19 -> 1.263148 | F5: ='Financial Data'!F20/'Financial Data'!F19 -> 0.6159595
A7: Coverage
A8: Interest Coverage (EBIT / Interest) | B8: ='Financial Data'!B9/'Financial Data'!B10 -> 1.0794121 | C8: ='Financial Data'!C9/'Financial Data'!C10 -> -0.012457045 | D8: ='Financial Data'!D9/'Financial Data'!D10 -> 0.6802934 | E8: ='Financial Data'!E9/'Financial Data'!E10 -> 4.0255465 | F8: ='Financial Data'!F9/'Financial Data'!F10 -> 6.4690144
A9: DSCR proxy (CFO / Interest) * | B9: ='Financial Data'!B26/'Financial Data'!B10 -> 3.5816969 | C9: ='Financial Data'!C26/'Financial Data'!C10 -> 1.5338273 | D9: ='Financial Data'!D26/'Financial Data'!D10 -> 3.4609291 | E9: ='Financial Data'!E26/'Financial Data'!E10 -> 8.9432447 | F9: ='Financial Data'!F26/'Financial Data'!F10 -> 12.414322
A11: Liquidity
A12: Working Capital Days (proxy) * | B12: ='Financial Data'!B29 -> -112 | C12: ='Financial Data'!C29 -> -88 | D12: ='Financial Data'!D29 -> -63 | E12: ='Financial Data'!E29 -> -55 | F12: ='Financial Data'!F29 -> -62
A14: Profitability
A15: EBITDA Margin % | B15: ='Financial Data'!B7 -> 0.12925399 | C15: ='Financial Data'!C7 -> 0.088775884 | D15: ='Financial Data'!D7 -> 0.091962528 | E15: ='Financial Data'!E7 -> 0.13319555 | F15: ='Financial Data'!F7 -> 0.12767487
A16: ROE (Net Profit / Net Worth) | B16: ='Financial Data'!B13/'Financial Data'!B19 -> -0.2424566 | C16: ='Financial Data'!C13/'Financial Data'!C19 -> -0.25378694 | D16: ='Financial Data'!D13/'Financial Data'!D19 -> 0.059353074 | E16: ='Financial Data'!E13/'Financial Data'!E19 -> 0.37456134 | F16: ='Financial Data'!F13/'Financial Data'!F19 -> 0.24236293
A17: ROCE % | B17: ='Financial Data'!B30 -> 0.06 | C17: ='Financial Data'!C30 -> 0.01 | D17: ='Financial Data'!D30 -> 0.06 | E17: ='Financial Data'!E30 -> 0.19 | F17: ='Financial Data'!F30 -> 0.2
A19: * Proxies used due to public data limitations - see README tab.
A21: Leverage & Coverage Trend (chart data)
A22: Metric | B22: FY2021 | C22: FY2022 | D22: FY2023 | E22: FY2024 | F22: FY2025
A23: Debt-to-Equity (x) | B23: =B5 -> 2.5726465 | C23: =C5 -> 3.2864837 | D23: =D5 -> 2.9591148 | E23: =E5 -> 1.263148 | F23: =F5 -> 0.6159595
A24: Interest Coverage (x) | B24: =B8 -> 1.0794121 | C24: =C8 -> -0.012457045 | D24: =D8 -> 0.6802934 | E24: =E8 -> 4.0255465 | F24: =F8 -> 6.4690144

Sheet Rating Scorecard
A1: Indicative Internal Credit Scorecard (FY2025, academic exercise)
A2: This is a simplified illustrative scorecard, not a rating agency (CRISIL/ICRA/CARE) methodology output.
A4: Factor | B4: FY2025 Value | C4: Score (1-5) | D4: Rationale
A5: Leverage (D/E) | B5: ='Ratio Analysis'!F5 -> 0.6159595 | C5: 5 | D5: D/E of 0.62x is low for a capital-intensive auto OEM - strong deleveraging since FY22 peak of 3.29x.
A6: Interest Coverage | B6: ='Ratio Analysis'!F8 -> 6.4690144 | C6: 5 | D6: 6.47x EBIT/Interest comfortably covers debt service; up from sub-1x in FY21-22.
A7: DSCR proxy | B7: ='Ratio Analysis'!F9 -> 12.414322 | C7: 5 | D7: CFO/Interest of ~12.4x reflects strong operating cash generation relative to interest burden.
A8: Profitability (EBITDA margin) | B8: ='Ratio Analysis'!F15 -> 0.12767487 | C8: 4 | D8: 13% margin restored to FY21 levels after a dip in FY22-23; in line with global auto OEM peers.
A9: Returns (ROCE) | B9: ='Ratio Analysis'!F17 -> 0.2 | C9: 4 | D9: 20% ROCE is strong, though still recovering from near-zero in FY22.
A10: Earnings volatility (5yr trend) | B10: - | C10: 2 | D10: PAT swung from -13,395 Cr (FY21) to +31,807 Cr (FY24) - high historical volatility (COVID, chip shortage, JLR restructuring).
A11: Liquidity (working capital structure) | B11: ='Ratio Analysis'!F12 -> -62 | C11: 4 | D11: Persistently negative working capital days reflect strong payables leverage typical of auto OEMs, not a liquidity strain.
A13: Weighted Average Score (equal-weighted) | C13: =AVERAGE(C5:C11) -> 4.1428571
A15: Indicative Internal Rating Band
A16: Score 4.5-5.0 = AA-equivalent | 3.5-4.4 = A-equivalent | 2.5-3.4 = BBB-equivalent | <2.5 = Sub-investment grade
A17: =IF(C13>=4.5,"AA-equivalent (indicative)",IF(C13>=3.5,"A-equivalent (indicative)",IF(C13>=2.5,"BBB-equivalent (indicative)","Sub-investment grade (indicative)"))) -> A-equivalent (indicative)
